jupyter_kernel_provisioner_proxy/__init__.py
jupyter_kernel_provisioner_proxy/cli.py
jupyter_kernel_provisioner_proxy/client.py
jupyter_kernel_provisioner_proxy/connect.py
jupyter_kernel_provisioner_proxy/message.py
jupyter_kernel_provisioner_proxy-0.1.1.dist-info/METADATA
jupyter_kernel_provisioner_proxy-0.1.1.dist-info/WHEEL
jupyter_kernel_provisioner_proxy-0.1.1.dist-info/entry_points.txt
jupyter_kernel_provisioner_proxy-0.1.1.dist-info/licenses/LICENSE
jupyter_kernel_provisioner_proxy-0.1.1.dist-info/RECORD
