Metadata-Version: 2.1
Name: jupyter-kernel-provisioner-proxy
Version: 0.1.1
Summary: Jupyter kernel provisioner proxy
Project-URL: Homepage, https://github.com/davidbrochart/jupyter-kernel-provisioner-proxy
Author-email: David Brochart <david.brochart@gmail.com>
License: MIT
License-File: LICENSE
Classifier: Development Status :: 4 - Beta
Classifier: Programming Language :: Python
Classifier: Programming Language :: Python :: 3.8
Classifier: Programming Language :: Python :: 3.9
Classifier: Programming Language :: Python :: 3.10
Classifier: Programming Language :: Python :: 3.11
Classifier: Programming Language :: Python :: Implementation :: CPython
Classifier: Programming Language :: Python :: Implementation :: PyPy
Requires-Python: >=3.8
Requires-Dist: httpx-ws<1,>=0.4.0
Requires-Dist: httpx<1,>=0.24.1
Requires-Dist: jupyter-client
Requires-Dist: python-dateutil
Requires-Dist: pyzmq
Requires-Dist: rich-click<2,>=1.6.1
Requires-Dist: wsproto
